addEvenNumbers/__init__.py
evenNumberAdd-1.0.dist-info/LICENSE.txt
evenNumberAdd-1.0.dist-info/METADATA
evenNumberAdd-1.0.dist-info/WHEEL
evenNumberAdd-1.0.dist-info/top_level.txt
evenNumberAdd-1.0.dist-info/RECORD
