Metadata-Version: 2.1
Name: evenNumberAdd
Version: 1.0
Summary: by using th erange you can add the even numbers evenNumberAdd
Home-page: UNKNOWN
Author: Atanu Mondal
Author-email: atanumondalbarjora@gmail.com
License: UNKNOWN
Platform: UNKNOWN
Classifier: Programming Language :: Python :: 3
Classifier: License :: OSI Approved :: MIT License
Classifier: Operating System :: OS Independent
